jflask/__init__.py
jflask/decorators.py
jflask/test_decorators.py
jflask-0.0.2.dist-info/LICENSE
jflask-0.0.2.dist-info/METADATA
jflask-0.0.2.dist-info/WHEEL
jflask-0.0.2.dist-info/top_level.txt
jflask-0.0.2.dist-info/RECORD
